aeronet_raster/__init__.py
aeronet_raster/__version__.py
aeronet_raster/collectionprocessor.py
aeronet_raster/merge.py
aeronet_raster/split.py
aeronet_raster/band/__init__.py
aeronet_raster/band/band.py
aeronet_raster/band/bandsample.py
aeronet_raster/bandcollection/__init__.py
aeronet_raster/bandcollection/bandcollection.py
aeronet_raster/bandcollection/bandcollectionsample.py
aeronet_raster/geoobject/__init__.py
aeronet_raster/geoobject/geoobject.py
aeronet_raster/utils/__init__.py
aeronet_raster/utils/calc_window_weight_mtrx.py
aeronet_raster/utils/coords.py
aeronet_raster/utils/utils.py
aeronet_raster-0.2.5.dist-info/METADATA
aeronet_raster-0.2.5.dist-info/WHEEL
aeronet_raster-0.2.5.dist-info/top_level.txt
aeronet_raster-0.2.5.dist-info/RECORD
