Metadata-Version: 2.1
Name: aeronet-raster
Version: 0.2.5
Summary: Raster operations for deep learning with remote sensing data. Based on Rasterio.
Home-page: 
Author: Geoalert
Author-email: hello@geoalert.io
License: MIT
Classifier: License :: OSI Approved :: MIT License
Classifier: Programming Language :: Python
Classifier: Programming Language :: Python :: 3
Classifier: Programming Language :: Python :: 3.6
Classifier: Programming Language :: Python :: Implementation :: CPython
Classifier: Programming Language :: Python :: Implementation :: PyPy
Requires-Python: >=3.6.0
Requires-Dist: numpy >=1.15.4
Requires-Dist: rasterio >=1.0.0
Requires-Dist: tqdm <4.65,>=4.36.1
